{"chunk_definitions":[{"chunk_id":"csetup_chunk","chunk_label":"setup","document_id":"6990DE06","expansion_state":0,"options":{"engine":"r","include":false},"row":11,"row_count":1,"visible":true},{"chunk_id":"c2cx6ra6l6878","chunk_label":"import r libraries","document_id":"6990DE06","expansion_state":0,"options":{"engine":"r"},"row":18,"row_count":1,"visible":true},{"chunk_id":"c0tdzpivpccd0","chunk_label":"import pyton libraries","document_id":"6990DE06","expansion_state":0,"options":{"engine":"python"},"row":23,"row_count":1,"visible":true},{"chunk_id":"c6toj8etltc42","chunk_label":"unnamed-chunk-1","document_id":"6990DE06","expansion_state":0,"options":{"engine":"python","label":"unnamed-chunk-5"},"row":58,"row_count":1,"visible":true},{"chunk_id":"cagc4v0ys62y4","chunk_label":"unnamed-chunk-2","document_id":"6990DE06","expansion_state":0,"options":{"engine":"python","label":"unnamed-chunk-6"},"row":67,"row_count":1,"visible":true}],"default_chunk_options":{"echo":true},"doc_write_time":1557921873,"working_dir":null}